infralens/__init__.py
infralens/app.py
infralens/cli.py
infralens/config.py
infralens/data.py
infralens/fetch.py
infralens/setup.py
infralens/screens/__init__.py
infralens/widgets/__init__.py
infralens-0.1.0.dist-info/METADATA
infralens-0.1.0.dist-info/WHEEL
infralens-0.1.0.dist-info/entry_points.txt
infralens-0.1.0.dist-info/licenses/LICENSE
infralens-0.1.0.dist-info/RECORD
