Metadata-Version: 2.4
Name: infralens
Version: 0.1.0
Summary: Terminal dashboard for cloud infrastructure - domains, hosting, and AI spend
Project-URL: Homepage, https://github.com/HamedMP/infralens
Project-URL: Repository, https://github.com/HamedMP/infralens
Project-URL: Issues, https://github.com/HamedMP/infralens/issues
Author: Hamed Mohammadpour
License-Expression: MIT
License-File: LICENSE
Keywords: cli,cloud,dashboard,devops,domains,infrastructure,tui
Classifier: Development Status :: 4 - Beta
Classifier: Environment :: Console
Classifier: Intended Audience :: Developers
Classifier: Intended Audience :: System Administrators
Classifier: License :: OSI Approved :: MIT License
Classifier: Operating System :: OS Independent
Classifier: Programming Language :: Python :: 3.12
Classifier: Programming Language :: Python :: 3.13
Classifier: Topic :: System :: Monitoring
Classifier: Topic :: System :: Systems Administration
Requires-Python: >=3.12
Requires-Dist: textual>=0.47.0
